<?xml version="1.0"?>
<block>
  <name>pymavlink_source_p</name>
  <key>uaslink_pymavlink_source_p</key>
  <category>[uaslink]</category>
  <import>import uaslink</import>
  <make>uaslink.pymavlink_source_p($connection_string, $baud_rate)</make>

  <param>
    <name>Baud Rate</name>
    <key>baud_rate</key>
    <value>57600</value>
    <type>int</type>
  </param>
  <param>
    <name>Connection String</name>
    <key>connection_string</key>
    <type>string</type>
  </param>

 
  <source>
    <name>MAVLink</name>
    <type>message</type>
    <optional>1</optional>
  </source>
</block>
